<metadata xml:lang="en"><Esri><CreaDate>20210308</CreaDate><CreaTime>15141300</CreaTime><ArcGISFormat>1.0</ArcGISFormat><SyncOnce>TRUE</SyncOnce><ModDate>20210408</ModDate><ModTime>22522300</ModTime><scaleRange><minScale>150000000</minScale><maxScale>5000</maxScale></scaleRange><ArcGISProfile>ItemDescription</ArcGISProfile></Esri><tool name="ExportROIPACdem" displayname="Export ROIPAC DEM" toolboxalias="ista" xmlns=""><arcToolboxHelpPath>c:\program files (x86)\arcgis\desktop10.7\Help\gp</arcToolboxHelpPath><parameters><param name="in_raster" displayname="Input Elevation Raster" type="Required" direction="Input" datatype="Raster Layer" expression="in_raster"><dialogReference>&lt;DIV STYLE="text-align:Left;"&gt;&lt;DIV&gt;&lt;DIV&gt;&lt;P&gt;&lt;SPAN&gt;This input raster must be in geographic coordinates (not UTM or Web Mercator).&lt;/SPAN&gt;&lt;/P&gt;&lt;/DIV&gt;&lt;/DIV&gt;&lt;/DIV&gt;</dialogReference></param><param name="output_name" displayname="Output name" type="Required" direction="Input" datatype="String" expression="output_name"><dialogReference>&lt;DIV STYLE="text-align:Left;"&gt;&lt;DIV&gt;&lt;P&gt;&lt;SPAN&gt;No special characters are allowed in this filename except underscore! &lt;/SPAN&gt;&lt;/P&gt;&lt;P&gt;&lt;SPAN&gt;The output files are named &amp;lt;output_name&amp;gt;.dem and &amp;lt;output_name&amp;gt;.dem.rsc&lt;/SPAN&gt;&lt;/P&gt;&lt;/DIV&gt;&lt;/DIV&gt;</dialogReference></param><param name="output_folder" displayname="Output folder" type="Required" direction="Input" datatype="Folder" expression="output_folder"><dialogReference>&lt;DIV STYLE="text-align:Left;"&gt;&lt;DIV&gt;&lt;P&gt;&lt;SPAN&gt;Output to this folder will include:&lt;/SPAN&gt;&lt;/P&gt;&lt;UL&gt;&lt;LI&gt;&lt;P&gt;&lt;SPAN&gt;&amp;lt;output_name&amp;gt;.dem - 16-bit unsigned bil raster&lt;/SPAN&gt;&lt;/P&gt;&lt;/LI&gt;&lt;LI&gt;&lt;P&gt;&lt;SPAN&gt;&amp;lt;output_name&amp;gt;.dem.rsc - header file used by roi_pac to read image&lt;/SPAN&gt;&lt;/P&gt;&lt;/LI&gt;&lt;LI&gt;&lt;P&gt;&lt;SPAN&gt;&amp;lt;output_name&amp;gt;_tif.tif - TIF file (same contents as the binary raster, for troubleshooting)&lt;/SPAN&gt;&lt;/P&gt;&lt;/LI&gt;&lt;/UL&gt;&lt;/DIV&gt;&lt;/DIV&gt;</dialogReference></param><param name="unix_path" displayname="Unix path" type="Required" direction="Input" datatype="String" expression="unix_path"><dialogReference>&lt;DIV STYLE="text-align:Left;"&gt;&lt;DIV&gt;&lt;P&gt;&lt;SPAN&gt;This is the unix path used on the destination machine. This path is written to the .rsc file and can be edited later.&lt;/SPAN&gt;&lt;/P&gt;&lt;/DIV&gt;&lt;/DIV&gt;</dialogReference></param><param name="agg_factor" displayname="Aggregation factor" type="Optional" direction="Input" datatype="Long" expression="{agg_factor}"><dialogReference>&lt;DIV STYLE="text-align:Left;"&gt;&lt;DIV&gt;&lt;DIV&gt;&lt;P&gt;&lt;SPAN&gt;Generalizes the output DEM by the specified factor. For example, if the value 2 is specified for a 1/3 arc-second (about 30 m) input DEM, the output will be a 2/3 arc-second raster (about 60 m).&lt;/SPAN&gt;&lt;/P&gt;&lt;P&gt;&lt;SPAN&gt;If set to 1 (default), no generalzation is done.&lt;/SPAN&gt;&lt;/P&gt;&lt;/DIV&gt;&lt;/DIV&gt;&lt;/DIV&gt;</dialogReference></param></parameters><summary>&lt;DIV STYLE="text-align:Left;"&gt;&lt;DIV&gt;&lt;DIV&gt;&lt;P&gt;&lt;SPAN&gt;This tool converts an ArcGIS raster to an unsigned integer DEM image file for use with ROIPAC.  A TIFF file is also created to verify the image output for troubleshooting purposes.&lt;/SPAN&gt;&lt;/P&gt;&lt;/DIV&gt;&lt;/DIV&gt;&lt;/DIV&gt;</summary></tool><dataIdInfo><idCitation><resTitle>Export ROIPAC DEM</resTitle></idCitation><searchKeys><keyword>insar</keyword><keyword>roipac</keyword></searchKeys><idAbs>&lt;DIV STYLE="text-align:Left;"&gt;&lt;DIV&gt;&lt;DIV&gt;&lt;P&gt;&lt;SPAN&gt;This tool converts an ArcGIS raster to an unsigned integer DEM image file for use with ROIPAC.  A TIFF file is also created to verify the image output for troubleshooting purposes.&lt;/SPAN&gt;&lt;/P&gt;&lt;/DIV&gt;&lt;/DIV&gt;&lt;/DIV&gt;</idAbs></dataIdInfo><distInfo><distributor><distorFormat><formatName>ArcToolbox Tool</formatName></distorFormat></distributor></distInfo><mdHrLv><ScopeCd value="005"/></mdHrLv><mdDateSt Sync="TRUE">20210408</mdDateSt></metadata>
